{"haikus": 
     [
          {"title": "Supernormal",
          "poem": "Starting to feel me\nNormal but with added good\nReady to spin now"
          },
          {
          "title": "Honey",
          "poem": "Buzzing thoughts and fears\nSwarm around my head like bees\nI hope there's honey"
          },
          {
          "title": "Tipping over",
          "poem": "Cold nip in the air\nMornings are growing darker\nThe year tips over"
          },
          {
          "title": "Early morning",
          "poem": "Up far too early\nWriting poetry at dawn\nBird song woke me up"
          },
          {
          "title": "What we love about skillful haiku poetry",
          "poem": "What we love about\nSkillful haiku poetry:\nSoulful brevity."
          },
          {
          "title": "Swallows flown away",
          "poem": "Can silence echo?\nThe weight of absence heavy\nSwallows flown away"
          },
          {
          "title": "Train haiku",
          "poem": "Chattering classes\nYoung girls putting on makeup\nCommuting to work"
          },
          {
          "title": "Heliotropic",
          "poem": "Here on the platform\nWe turn to the rising sun\nHeliotropic"
          },
          {
          "title": "Morning haiku",
          "link": "Free coffee refills\nSide of hot buttery toast\nBless the Waffle Barn"
          },
          {
          "title": "Haiku for home",
          "link": "The bird sings loudly\nHe can see the clear blue sky\nThrough the birdcage bars"
          },
          {
          "title": "The Old Box",
          "link": "I held the old box\nBut didn't open it - yet\nIgnorance is bliss"
          },
          {"title": "Memories of love",
          "poem": "Memories of love\nReleased at last from darkness\nAmazed us all"
          },
          {
          "title": "Haiku",
          "link": "A beautiful dress\nLike blossom on cherry boughs\nWhispering of spring"
          },
          {
          "title": "Apple Haiku",
          "link": "Apples, swollen, red,\nTwisting in the wind, waiting\nFor Fall, and falling."
          },
          {
          "title": "Blue Cornish Morning",
          "link": "Blue Cornish morning\nBright sun mirrored in the sea\nIt's Summer's last shout"
          },
          {
          "title": "On walking through Princes Street Gardens",
          "link": "A scatter of leaves,\nVermillion and yellow:\nThe year's bright decline."
          },
          {
          "title": "Now winter you say?",
          "link": "Now winter you say?\nThen why do bulbs push up hard\nIn January?"
          },
          {
          "title": "The slivered old moon",
          "link": "The slivered old moon\nLike a splinter from my heart\nAlmost worn away"
          }
     ]
}